README.md
setup.py
db2twitter/__init__.py
db2twitter/buildmessages.py
db2twitter/cfgparse.py
db2twitter/cliparse.py
db2twitter/dbparse.py
db2twitter/getdblasttweets.py
db2twitter/getnewmessages.py
db2twitter/imagesize.py
db2twitter/main.py
db2twitter/sendmessages.py
db2twitter/sqliteparse.py
db2twitter/sqlitesession.py
db2twitter/storestatus.py
db2twitter/timetosend.py
db2twitter/wasposted.py
db2twitter.egg-info/PKG-INFO
db2twitter.egg-info/SOURCES.txt
db2twitter.egg-info/dependency_links.txt
db2twitter.egg-info/requires.txt
db2twitter.egg-info/top_level.txt
db2twitter/cfgparsers/__init__.py
db2twitter/cfgparsers/mastodon.py
db2twitter/cfgparsers/media.py
db2twitter/cfgparsers/messages.py
db2twitter/cfgparsers/redis.py
db2twitter/cfgparsers/timer.py
db2twitter/cfgparsers/twitter.py
db2twitter/networks/__init__.py
db2twitter/networks/mastodon.py
db2twitter/networks/twitter.py
scripts/db2twitter