Metadata-Version: 1.1
Name: db2twitter
Version: 0.10
Summary: extract info from a database and send it to twitter
Home-page: https://gitlab.com/chaica/db2twitter
Author: Carl Chenet
Author-email: chaica@ohmytux.com
License: GNU GPL v3
Download-URL: https://gitlab.com/chaica/db2twitter
Platform: UNKNOWN
Classifier: Intended Audience :: End Users/Desktop
Classifier: Environment :: Console
Classifier: License :: OSI Approved :: GNU General Public License (GPL)
Classifier: Operating System :: POSIX :: Linux
Classifier: Programming Language :: Python :: 3.5
Classifier: Programming Language :: Python :: 3.6
